CxAdmin/__init__.py
CxAdmin/api/__init__.py
CxAdmin/api/cxEnvironment.py
CxAdmin/api/cxFlows.py
CxAdmin/api/cxItem.py
CxAdmin/api/cxLists.py
CxAdmin/api/cxQueues.py
CxAdmin/api/cxStatistics.py
CxAdmin/api/http/__init__.py
CxAdmin/api/http/httpClientModel.py
CxAdmin/api/http/httpclient.py
CxAdmin/objects/__init__.py
CxAdmin/objects/cx.py
CxAdmin/objects/cxList.py
CxAdmin/objects/cxQueue.py
CxAdmin-1.0.221.dist-info/METADATA
CxAdmin-1.0.221.dist-info/WHEEL
CxAdmin-1.0.221.dist-info/top_level.txt
CxAdmin-1.0.221.dist-info/RECORD
